{"is_source_file": true, "format": "JavaScript (React JSX)", "description": "This file defines a React component 'AppLayout' which provides the main layout structure for a personal finance tracking application. It includes a sidebar with navigation links, a header with action buttons, a main content area with Outlet for routed components, and a footer.", "external_files": ["react-router-dom"], "external_methods": ["NavLink", "Outlet"], "published": ["AppLayout"], "classes": [], "methods": [{"name": "SidebarLink({ to, label, icon })", "description": "A React functional component that renders a navigation link with an icon and label, highlighting when active.", "scope": "", "scopeKind": ""}, {"name": "AppLayout()", "description": "Main React component providing the application's layout with navigation sidebar, header, content section, and footer.", "scope": "", "scopeKind": ""}], "calls": ["react-router-dom.NavLink", "react-router-dom.Outlet", "new Date().getFullYear()"], "search-terms": ["React layout component", "Sidebar navigation", "Expense Tracker UI", "AppLayout"], "state": 2, "file_id": 15, "knowledge_revision": 68, "git_revision": "28ed1cf8367c86a9989f7a7207223e3b7f0d4d13", "revision_history": [{"31": ""}, {"64": "28ed1cf8367c86a9989f7a7207223e3b7f0d4d13"}, {"66": "28ed1cf8367c86a9989f7a7207223e3b7f0d4d13"}, {"67": "28ed1cf8367c86a9989f7a7207223e3b7f0d4d13"}, {"68": "28ed1cf8367c86a9989f7a7207223e3b7f0d4d13"}], "ctags": [{"_type": "tag", "name": "AppLayout", "path": "/home/kavia/workspace/code-generation/personal-finance-tracker-167375-167384/expense_tracker_frontend/src/AppLayout.js", "pattern": "/^export default function AppLayout() {$/", "language": "JavaScript", "kind": "function", "signature": "()"}, {"_type": "tag", "name": "SidebarLink", "path": "/home/kavia/workspace/code-generation/personal-finance-tracker-167375-167384/expense_tracker_frontend/src/AppLayout.js", "pattern": "/^function SidebarLink({ to, label, icon }) {$/", "language": "JavaScript", "kind": "function", "signature": "({ to, label, icon })"}, {"_type": "tag", "name": "to", "path": "/home/kavia/workspace/code-generation/personal-finance-tracker-167375-167384/expense_tracker_frontend/src/AppLayout.js", "pattern": "/^      to={to}$/", "language": "JavaScript", "kind": "field", "scope": "SidebarLink.to", "scopeKind": "class"}], "hash": "079d4a6bd2ad223e623bf58e1817def6", "format-version": 4, "code-base-name": "expense_tracker_frontend", "filename": "expense_tracker_frontend/src/AppLayout.js", "fields": [{"name": "to={to}", "scope": "SidebarLink.to", "scopeKind": "class", "description": "unavailable"}]}